polars_redis/__init__.py
polars_redis/_cache.py
polars_redis/_decorator.py
polars_redis/_infer.py
polars_redis/_internal.cpython-314-darwin.so
polars_redis/_pubsub.py
polars_redis/_read.py
polars_redis/_scan.py
polars_redis/_search.py
polars_redis/_streams.py
polars_redis/_utils.py
polars_redis/_write.py
polars_redis/options.py
polars_redis/py.typed
polars_redis/query.py
polars_redis-0.1.6.dist-info/METADATA
polars_redis-0.1.6.dist-info/WHEEL
polars_redis-0.1.6.dist-info/licenses/LICENSE-APACHE
polars_redis-0.1.6.dist-info/licenses/LICENSE-MIT
polars_redis-0.1.6.dist-info/RECORD
